furiosa/device/__init__.py
furiosa/device/git_version.txt
furiosa/device/py.typed
furiosa/device/sync.py
furiosa_device-0.10.2.dist-info/WHEEL
furiosa_device-0.10.2.dist-info/METADATA
furiosa_device-0.10.2.dist-info/RECORD
